sub_folder_1996/__init__.py
sub_folder_1996/tinh_tich_thuong.py
sub_folder_1996/tinh_tong_hieu.py
name_of_package_19961996-0.1.1.dist-info/METADATA
name_of_package_19961996-0.1.1.dist-info/WHEEL
name_of_package_19961996-0.1.1.dist-info/top_level.txt
name_of_package_19961996-0.1.1.dist-info/RECORD
