Metadata-Version: 2.4
Name: name_of_package_19961996
Version: 0.1.1
Summary: Demo package upload lên PyPI
Author: Chiêu Nguyễn
Author-email: your_email@example.com
Requires-Python: >=3.8
Dynamic: author
Dynamic: author-email
Dynamic: description
Dynamic: description-content-type
Dynamic: requires-python
Dynamic: summary
